chinese_whispers/__init__.py
chinese_whispers/__main__.py
chinese_whispers/chinese_whispers.py
chinese_whispers/py.typed
chinese_whispers/test_chinese_whispers.py
chinese_whispers-0.9.0.dist-info/LICENSE
chinese_whispers-0.9.0.dist-info/METADATA
chinese_whispers-0.9.0.dist-info/WHEEL
chinese_whispers-0.9.0.dist-info/entry_points.txt
chinese_whispers-0.9.0.dist-info/top_level.txt
chinese_whispers-0.9.0.dist-info/zip-safe
chinese_whispers-0.9.0.dist-info/RECORD
