Metadata-Version: 2.1
Name: chinese_whispers
Version: 0.9.0
Summary: An implementation of the Chinese Whispers clustering algorithm.
Author: Dmitry Ustalov
License: MIT
Project-URL: Homepage, https://github.com/nlpub/chinese-whispers
Project-URL: Documentation, https://chinese-whispers.readthedocs.io
Project-URL: Download, https://pypi.org/project/chinese-whispers/#files
Project-URL: Repository, https://github.com/nlpub/chinese-whispers
Keywords: graph clustering,unsupervised learning,chinese whispers,cluster analysis
Classifier: Development Status :: 5 - Production/Stable
Classifier: Intended Audience :: Developers
Classifier: Intended Audience :: Science/Research
Classifier: License :: OSI Approved :: MIT License
Classifier: Operating System :: OS Independent
Classifier: Programming Language :: Python :: 3
Classifier: Programming Language :: Python :: 3.8
Classifier: Programming Language :: Python :: 3.9
Classifier: Programming Language :: Python :: 3.10
Classifier: Programming Language :: Python :: 3.11
Classifier: Programming Language :: Python :: 3.12
Classifier: Programming Language :: Python :: Implementation :: CPython
Classifier: Programming Language :: Python :: Implementation :: PyPy
Classifier: Topic :: Scientific/Engineering :: Artificial Intelligence
Classifier: Topic :: Scientific/Engineering :: Information Analysis
Classifier: Typing :: Typed
Requires-Python: ~=3.8
License-File: LICENSE
Requires-Dist: networkx <4.0,>=2.1
Provides-Extra: dev
Requires-Dist: build ; extra == 'dev'
Requires-Dist: matplotlib ; extra == 'dev'
Requires-Dist: mypy ; extra == 'dev'
Requires-Dist: nbqa ; extra == 'dev'
Requires-Dist: notebook ; extra == 'dev'
Requires-Dist: pytest ; extra == 'dev'
Requires-Dist: ruff ; extra == 'dev'
Requires-Dist: twine ; extra == 'dev'
Requires-Dist: types-networkx ; extra == 'dev'
Provides-Extra: docs
Requires-Dist: mkdocs-material ; extra == 'docs'
Requires-Dist: mkdocstrings-python ; extra == 'docs'
